odoo/addons/chained_swapper/README.rst
odoo/addons/chained_swapper/__init__.py
odoo/addons/chained_swapper/__manifest__.py
odoo/addons/chained_swapper/hooks.py
odoo/addons/chained_swapper/demo/chained_swapper_demo.xml
odoo/addons/chained_swapper/i18n/chained_swapper.pot
odoo/addons/chained_swapper/i18n/es.po
odoo/addons/chained_swapper/i18n/it.po
odoo/addons/chained_swapper/models/__init__.py
odoo/addons/chained_swapper/models/chained_swapper.py
odoo/addons/chained_swapper/readme/CONFIGURE.md
odoo/addons/chained_swapper/readme/CONTRIBUTORS.md
odoo/addons/chained_swapper/readme/DESCRIPTION.md
odoo/addons/chained_swapper/readme/USAGE.md
odoo/addons/chained_swapper/security/ir.model.access.csv
odoo/addons/chained_swapper/static/description/icon.png
odoo/addons/chained_swapper/static/description/index.html
odoo/addons/chained_swapper/tests/__init__.py
odoo/addons/chained_swapper/tests/test_chained_swapper.py
odoo/addons/chained_swapper/views/chained_swapper_views.xml
odoo/addons/chained_swapper/wizard/__init__.py
odoo/addons/chained_swapper/wizard/chained_swapper_wizard.py
odoo/addons/chained_swapper/wizard/chained_swapper_wizard_views.xml
odoo_addon_chained_swapper-18.0.1.0.0.3.dist-info/METADATA
odoo_addon_chained_swapper-18.0.1.0.0.3.dist-info/WHEEL
odoo_addon_chained_swapper-18.0.1.0.0.3.dist-info/top_level.txt
odoo_addon_chained_swapper-18.0.1.0.0.3.dist-info/RECORD
